minismu_py/__init__.py
minismu_py/smu.py
minismu_py-0.3.0.dist-info/licenses/LICENSE
minismu_py-0.3.0.dist-info/METADATA
minismu_py-0.3.0.dist-info/WHEEL
minismu_py-0.3.0.dist-info/top_level.txt
minismu_py-0.3.0.dist-info/RECORD
