Metadata-Version: 2.4
Name: minismu_py
Version: 0.3.0
Summary: Python interface library for Undalogic miniSMU devices
Home-page: https://github.com/Undalogic/minismu_py
Author: Undalogic
Author-email: joel.troughton@undalogic.com
Project-URL: Bug Tracker, https://github.com/Undalogic/minismu_py/issues
Classifier: Development Status :: 3 - Alpha
Classifier: Intended Audience :: Science/Research
Classifier: License :: OSI Approved :: MIT License
Classifier: Operating System :: OS Independent
Classifier: Programming Language :: Python :: 3
Classifier: Programming Language :: Python :: 3.6
Classifier: Programming Language :: Python :: 3.7
Classifier: Programming Language :: Python :: 3.8
Classifier: Programming Language :: Python :: 3.9
Classifier: Programming Language :: Python :: 3.10
Classifier: Programming Language :: Python :: 3.11
Requires-Python: >=3.6
License-File: LICENSE
Requires-Dist: pyserial>=3.5
Provides-Extra: dev
Requires-Dist: tqdm>=4.65.0; extra == "dev"
Dynamic: author
Dynamic: classifier
Dynamic: description
Dynamic: description-content-type
Dynamic: home-page
Dynamic: license-file
Dynamic: project-url
Dynamic: provides-extra
Dynamic: requires-dist
Dynamic: requires-python
Dynamic: summary
